shimmer_listener/__init__.py
shimmer_listener/_master.py
shimmer_listener/_slave.py
shimmer_listener/_streams.py
shimmer_listener/console_scripts.py
shimmer_listener-0.4.0.data/data/LICENSE
shimmer_listener-0.4.0.dist-info/LICENSE
shimmer_listener-0.4.0.dist-info/METADATA
shimmer_listener-0.4.0.dist-info/WHEEL
shimmer_listener-0.4.0.dist-info/entry_points.txt
shimmer_listener-0.4.0.dist-info/top_level.txt
shimmer_listener-0.4.0.dist-info/RECORD
