Metadata-Version: 2.1
Name: shimmer-listener
Version: 0.4.0
Summary: A library to process bluetooth data from a shimmer2 runnning tinyos
Home-page: UNKNOWN
Author: Gianmarco Marcello
Author-email: g.marcello@antima.it
License: GPLv2.0
Platform: UNKNOWN
Requires-Python: >=3.6
License-File: LICENSE
Requires-Dist: pybluez
